mqtt_homeassistant_utils/__init__.py
mqtt_homeassistant_utils/base.py
mqtt_homeassistant_utils/binarysensor.py
mqtt_homeassistant_utils/climate.py
mqtt_homeassistant_utils/cover.py
mqtt_homeassistant_utils/mqttclient.py
mqtt_homeassistant_utils/select.py
mqtt_homeassistant_utils/sensor.py
mqtt_homeassistant_utils/switch.py
mqtt_homeassistant_utils/water_heater.py
mqtt_homeassistant_utils-0.0.10.dist-info/LICENSE
mqtt_homeassistant_utils-0.0.10.dist-info/METADATA
mqtt_homeassistant_utils-0.0.10.dist-info/WHEEL
mqtt_homeassistant_utils-0.0.10.dist-info/top_level.txt
mqtt_homeassistant_utils-0.0.10.dist-info/RECORD
