Metadata-Version: 2.1
Name: mqtt_homeassistant_utils
Version: 0.0.10
Summary: A helper project to work with the mqtt integraton in home assistant
Author: Sebastian Wienecke
License: MIT License
Project-URL: Homepage, https://github.com/Xembalo/mqtt-homeassistant-utils
Project-URL: Issues, https://github.com/Xembalo/mqtt-homeassistant-utils/issues
Project-URL: Repository, https://github.com/Xembalo/mqtt-homeassistant-utils.git
Keywords: mqtt,home assistant,hass,homeassistant,auto discovery
Classifier: Development Status :: 2 - Pre-Alpha
Classifier: Programming Language :: Python :: 3
Classifier: License :: OSI Approved :: MIT License
Classifier: Operating System :: OS Independent
Classifier: Topic :: Software Development :: Libraries :: Python Modules
Requires-Python: >=3.11
License-File: LICENSE
Requires-Dist: paho-mqtt>=2.1.0
